{
    "prepare_queue": {
        "installed": [],
        "uninstalled": []
    },
    "config_munge": {
        "files": {
            "res/xml/config.xml": {
                "parents": {
                    "/*": [
                        {
                            "xml": "<feature name=\"HttpClient\"><param name=\"android-package\" value=\"com.pedox.plugin.HttpClient.HttpClient\" /></feature>",
                            "count": 1
                        },
                        {
                            "xml": "<feature name=\"InAppBrowser\"><param name=\"android-package\" value=\"org.apache.cordova.inappbrowser.InAppBrowser\" /></feature>",
                            "count": 1
                        },
                        {
                            "xml": "<feature name=\"NetworkStatus\"><param name=\"android-package\" value=\"org.apache.cordova.networkinformation.NetworkManager\" /></feature>",
                            "count": 1
                        }
                    ]
                }
            },
            "AndroidManifest.xml": {
                "parents": {
                    "/manifest": [
                        {
                            "xml": "<uses-permission android:name=\"android.permission.INTERNET\" />",
                            "count": 1
                        }
                    ],
                    "/*": [
                        {
                            "xml": "<uses-permission android:name=\"android.permission.ACCESS_NETWORK_STATE\" />",
                            "count": 1
                        }
                    ]
                }
            }
        }
    },
    "installed_plugins": {
        "cordova-httpclient": {
            "PACKAGE_NAME": "com.ionicframework.binusmayamini364957"
        },
        "cordova-plugin-inappbrowser": {
            "PACKAGE_NAME": "com.ionicframework.binusmayamini364957"
        },
        "cordova-plugin-network-information": {
            "PACKAGE_NAME": "com.ionicframework.binusmayamini364957"
        }
    },
    "dependent_plugins": {}
}